pygofile/__init__.py
pygofile/gofile.py
tests/__init__.py
tests/test_all.py
pygofile-1.0.2.dist-info/LICENSE
pygofile-1.0.2.dist-info/METADATA
pygofile-1.0.2.dist-info/WHEEL
pygofile-1.0.2.dist-info/top_level.txt
pygofile-1.0.2.dist-info/RECORD
